{
  "raceId": "P4_S4_control_R18_Singapore",
  "participantId": "P4",
  "date": "2026-02-01T22:42:31.209Z",
  "track": "Singapore",
  "trackId": 12,
  "seasonType": "control",
  "seasonNumber": 4,
  "raceNumber": 18,
  "totalLaps": 16,
  "difficulty": 80,
  "startingPosition": 19,
  "finishPosition": 6,
  "points": 8,
  "fastestLap": false,
  "bestLapMs": 95829,
  "avgLapMs": 103085,
  "pitStops": [
    {
      "lap": 9,
      "compoundFrom": "Medium",
      "compoundTo": "Hard",
      "positionBefore": 1,
      "positionAfter": 1,
      "triggeredBy": "driver",
      "llmRecommendedLap": null
    }
  ],
  "totalPitStops": 1,
  "weatherChanges": [],
  "safetyCars": 1,
  "virtualSafetyCars": 0,
  "llmTotalCalls": 31,
  "llmAvgLatencyMs": 3216,
  "llmStrategyCommits": 1,
  "llmStrategyAmends": 3,
  "llmERSCalls": 7,
  "llmDriverQuestions": 20,
  "followedRate": 0,
  "notes": "Strategy Quality: correct. 1 stop on lap9 M->H. Just couldn't pass P5 otherwise great drive\n"
}